drf_contact/__init__.py
drf_contact/admin.py
drf_contact/apps.py
drf_contact/models.py
drf_contact/serializers.py
drf_contact/tests.py
drf_contact/urls.py
drf_contact/views.py
drf_contact/migrations/0001_initial.py
drf_contact/migrations/__init__.py
drf_contact-0.0.2.dist-info/METADATA
drf_contact-0.0.2.dist-info/RECORD
drf_contact-0.0.2.dist-info/WHEEL
drf_contact-0.0.2.dist-info/top_level.txt
