Metadata-Version: 2.1
Name: drf-contact
Version: 0.0.2
Summary: Contact APP for Django REST Framework with API Views.
Home-page: https://github.com/civilmachines/drf-contact
Author: Civil Machines Technologies Private Limited
Author-email: pypidev@civilmachines.com
License: GPLv3
Platform: UNKNOWN
Classifier: Environment :: Web Environment
Classifier: Framework :: Django
Classifier: Framework :: Django :: 1.10
Classifier: Framework :: Django :: 1.11
Classifier: Framework :: Django :: 2.0
Classifier: Intended Audience :: Developers
Classifier: License :: OSI Approved :: GNU General Public License v3 (GPLv3)
Classifier: Operating System :: OS Independent
Classifier: Programming Language :: Python
Classifier: Programming Language :: Python :: 3
Classifier: Programming Language :: Python :: 3.4
Classifier: Programming Language :: Python :: 3.5
Classifier: Programming Language :: Python :: 3.6
Classifier: Topic :: Internet :: WWW/HTTP
Requires-Python: >=2.7, !=3.0.*, !=3.1.*, !=3.2.*, !=3.3.*
Requires-Dist: Django (>=2.0.7)
Requires-Dist: django-filter (>=1.1.0)
Requires-Dist: djangorestframework (>=3.8.2)
Requires-Dist: drfaddons (>=0.0.1)
Requires-Dist: pytz (>=2018.5)
